pyscratch/pyscratch.py
pyscratch/run.py
pyscratch/Asset/Button/RunButton.py
pyscratch/Asset/Button/StopButton.py
pyscratch/Asset/Core/object.py
pyscratch/Asset/Core/text.py
pyscratch/Asset/Core/Sprite/control.py
pyscratch/Asset/Core/Sprite/core.py
pyscratch/Asset/Core/Sprite/draw.py
pyscratch/Asset/Core/Sprite/events.py
pyscratch/Asset/Core/Sprite/looks.py
pyscratch/Asset/Core/Sprite/motion.py
pyscratch/Asset/Core/Sprite/sensing.py
pyscratch/Asset/Core/Sprite/sound.py
pyscratch/Asset/Core/Sprite/variable.py
pyscratch/Asset/Image/RunButton.png
pyscratch/Asset/Image/StopButton.png
pyscratch/Sprite/code.py
pyscratch/Sprite/sprite.py
pyscratch_lobotmy2012-0.1.4.dist-info/licenses/LICENSE
pyscratch_lobotmy2012-0.1.4.dist-info/METADATA
pyscratch_lobotmy2012-0.1.4.dist-info/WHEEL
pyscratch_lobotmy2012-0.1.4.dist-info/top_level.txt
pyscratch_lobotmy2012-0.1.4.dist-info/RECORD
