Metadata-Version: 2.4
Name: pyscratch-lobotmy2012
Version: 0.1.4
Summary: A Scratch-like game engine built with Pygame
Author-email: Lobotomy2012 <luongnaman0906.amongus@gmail.com>
License: MIT License
Project-URL: Homepage, https://github.com/Lobotomy2012/PyScratch
Requires-Python: >=3.8
License-File: LICENSE
Requires-Dist: pygame>=2.6.0
Dynamic: license-file
